conreality/__init__.py
conreality/sdk/__init__.py
conreality/sdk/asset.py
conreality/sdk/binary.py
conreality/sdk/camera.py
conreality/sdk/client.py
conreality/sdk/event.py
conreality/sdk/message.py
conreality/sdk/object.py
conreality/sdk/player.py
conreality/sdk/session.py
conreality/sdk/theater.py
conreality-0.0.4.dist-info/METADATA
conreality-0.0.4.dist-info/UNLICENSE
conreality-0.0.4.dist-info/WHEEL
conreality-0.0.4.dist-info/top_level.txt
conreality-0.0.4.dist-info/RECORD
