Metadata-Version: 2.1
Name: conreality
Version: 0.0.4
Summary: Conreality Software Development Kit (SDK) for Python
Home-page: https://sdk.conreality.org/python/
Author: Conreality.org
Author-email: conreality@googlegroups.com
License: Public Domain
Project-URL: Source, https://github.com/conreality/conreality.py
Keywords: conreality sdk driver robotics
Platform: UNKNOWN
Classifier: Development Status :: 3 - Alpha
Classifier: Environment :: Console
Classifier: Intended Audience :: Developers
Classifier: Intended Audience :: Information Technology
Classifier: Intended Audience :: Science/Research
Classifier: License :: Public Domain
Classifier: Natural Language :: English
Classifier: Operating System :: MacOS :: MacOS X
Classifier: Operating System :: POSIX
Classifier: Programming Language :: Python :: 3 :: Only
Classifier: Programming Language :: Python :: 3.7
Classifier: Topic :: Games/Entertainment :: Simulation
Classifier: Topic :: Scientific/Engineering :: Human Machine Interfaces
Classifier: Topic :: Software Development :: Embedded Systems
Classifier: Topic :: System :: Hardware :: Hardware Drivers
Requires-Python: ~=3.7
Requires-Dist: drylib
Requires-Dist: grpcio (>=1.15)
Requires-Dist: numpy (>=1.15)
Provides-Extra: test
Requires-Dist: pytest; extra == 'test'
